<annotation>
	<folder>mobiliario</folder>
	<filename>H-5.2018.05.03.16.17.28.340.bmp</filename>
	<path>/home/gustavo/Documentos/framework/data/mobiliario/H-5.2018.05.03.16.17.28.340.bmp</path>
	<source>
		<database>Unknown</database>
	</source>
	<size>
		<width>352</width>
		<height>240</height>
		<depth>3</depth>
	</size>
	<segmented>0</segmented>
	<object>
		<name>ocupado</name>
		<pose>Unspecified</pose>
		<truncated>0</truncated>
		<difficult>0</difficult>
		<bndbox>
			<xmin>46</xmin>
			<ymin>44</ymin>
			<xmax>167</xmax>
			<ymax>131</ymax>
		</bndbox>
	</object>
	<object>
		<name>libre</name>
		<pose>Unspecified</pose>
		<truncated>0</truncated>
		<difficult>0</difficult>
		<bndbox>
			<xmin>212</xmin>
			<ymin>47</ymin>
			<xmax>297</xmax>
			<ymax>152</ymax>
		</bndbox>
	</object>
	<object>
		<name>libre</name>
		<pose>Unspecified</pose>
		<truncated>1</truncated>
		<difficult>0</difficult>
		<bndbox>
			<xmin>86</xmin>
			<ymin>1</ymin>
			<xmax>168</xmax>
			<ymax>52</ymax>
		</bndbox>
	</object>
</annotation>
